{
  "joke.aow": [
    {
      "question": "Why did Poseidon and Selene break up?",
      "answer": "Because their relationship is *Poselene* (porcelain)",
      "credit": "Kitsune"
    },
    {
      "question": "What hero is really bad at basketball?",
      "answer": "Aly, because she keeps dropping the ball",
      "credit": "Kitsune"
    },
    {
      "question": "Why do mages skip school?",
      "answer": "Because they don't want to become scholars.",
      "credit": "Kitsune"
    },
    {
      "question": "How do you summon Azrael",
      "answer": "With **nun**-stopping praying",
      "credit": "Kitsune"
    },
    {
      "question": "Who is the most self-centered hero?",
      "answer": "Chi**one**",
      "credit": "Kitsune"
    },
    {
      "question": "Who won the AoW beauty pageant contest?",
      "answer": "Selene. She was just stunning.",
      "credit": "Harmless Buns"
    },
    {
      "question": "Why were Goblikazes booed off the stage in the concert?",
      "answer": "They totally bombed",
      "credit": "Harmless Buns"
    },
    {
      "joke<text>": [
        "One day, Ivan stormed into the developer's meeting and demanded buff to his skills",
        "",
        "The room was in total *silence*..."
      ],
      "credit": "Kitsune"
    },
    {
      "question": "Why did the Peltasts lose the marathon?",
      "answer": "They kept running backwards.",
      "credit": "Harmless Buns"
    },
    {
      "joke<text>": [
        "Aly was strolling in the woods when Miller suddenly stood up from a bush.",
        "Miller eyed Aly's tails and curiously asked “say, do your tails get sticky when you poo?”",
        "“Not at all,” Aly grinned.",
        "“Good!” Miller answered and grabbed one of Aly's tails to wipe his butt."
      ],
      "credit": "Jolihi Kan"
    },
    {
      "question": "If Zeus and Kraken competed in Olympics swimming, who would win?",
      "answer": "Neither, because Kraken won't survive in fresh water, and Zeus would electrocute himself.",
      "credit": "Harmless Buns"
    },
    {
      "question": "Who is Meteor Golem's favorite band?",
      "answer": "Rolling Stones",
      "credit": "Harmless Buns"
    }
  ]
}
